LICENSE
MANIFEST.in
requirements.txt
setup.py
clearner.egg-info/PKG-INFO
clearner.egg-info/SOURCES.txt
clearner.egg-info/dependency_links.txt
clearner.egg-info/entry_points.txt
clearner.egg-info/requires.txt
clearner.egg-info/top_level.txt
learner/__init__.py
learner/analysis/__init__.py
learner/analysis/analysis.py
learner/analysis/plot.py
learner/analysis/shap.py
learner/api_worker/__init__.py
learner/api_worker/google_drive.py
learner/callback_manager/__init__.py
learner/callback_manager/callback.py
learner/combine/__init__.py
learner/combine/combining_manager.py
learner/communication/__init__.py
learner/communication/communication_manager.py
learner/communication/email_manager.py
learner/configuration/__init__.py
learner/configuration/analysis.py
learner/configuration/column.py
learner/configuration/combine.py
learner/configuration/communication.py
learner/configuration/configuration.py
learner/configuration/connection.py
learner/configuration/data.py
learner/configuration/defaults.py
learner/configuration/dml.py
learner/configuration/feature_engineering.py
learner/configuration/model.py
learner/configuration/outlier.py
learner/configuration/process.py
learner/configuration/recommender.py
learner/configuration/sample.py
learner/configuration/segmenter.py
learner/configuration/similarities.py
learner/configuration/supported_items.py
learner/configuration/validation.py
learner/configuration/workspace.py
learner/data_worker/__init__.py
learner/data_worker/data_loader.py
learner/data_worker/data_manager.py
learner/data_worker/data_mover.py
learner/data_worker/data_processor.py
learner/data_worker/data_sampler.py
learner/data_worker/data_segmenters.py
learner/data_worker/data_set.py
learner/data_worker/deep_tabular_data_manager.py
learner/data_worker/image_data_loader.py
learner/data_worker/image_data_manager.py
learner/data_worker/image_processor.py
learner/data_worker/output_handler.py
learner/engines/__init__.py
learner/engines/base_deep_engine.py
learner/engines/base_standard_engine.py
learner/engines/deep_classifier.py
learner/engines/deep_regressor.py
learner/engines/dml.py
learner/engines/engine_manager.py
learner/engines/image_classifier.py
