Metadata-Version: 2.4
Name: clearner
Version: 1.0.2
Summary: Learner is a software platform for building production-ready machine learning models without writing any codes.
Home-page: https://prizmi.ai/learner/home
Author: Prizmi LLC
Author-email: contact@prizmi.ai
License: Other
Classifier: Development Status :: 4 - Beta
Classifier: Intended Audience :: Developers
Classifier: License :: Other/Proprietary License
Classifier: Programming Language :: Python :: 3
Classifier: Programming Language :: Python :: 3.12
Requires-Python: >=3.12,<3.13
License-File: LICENSE
Requires-Dist: pyarrow==15.0.2
Requires-Dist: fastparquet==2024.2.0
Requires-Dist: econml==0.15.1
Requires-Dist: pandas==2.2.2
Requires-Dist: scikit-learn==1.4.2
Requires-Dist: scipy==1.13.1
Requires-Dist: tqdm==4.66.4
Requires-Dist: dill==0.3.8
Requires-Dist: lightgbm==4.3.0
Requires-Dist: matplotlib==3.8.4
Requires-Dist: seaborn==0.13.2
Requires-Dist: shap==0.43.0
Requires-Dist: numba==0.59.1
Requires-Dist: valideer==0.4.2
Requires-Dist: xgboost==2.1.2
Requires-Dist: SQLAlchemy==2.0.36
Requires-Dist: cryptography==43.0.3
Requires-Dist: PyHive==0.7.0
Requires-Dist: thrift==0.16.0
Requires-Dist: pysasl==0.7.0
Requires-Dist: thrift-sasl==0.4.3
Requires-Dist: pure-sasl==0.6.2
Requires-Dist: pytest==8.3.4
Requires-Dist: pytest-xdist==3.6.1
Requires-Dist: mock==5.1.0
Requires-Dist: psycopg2-binary==2.9.10
Requires-Dist: mysql-connector-python==9.1.0
Requires-Dist: catboost==1.2.7
Requires-Dist: commentjson==0.9.0
Requires-Dist: torch==2.4.1
Requires-Dist: torchvision==0.19.1
Requires-Dist: jsonschema==4.23.0
Requires-Dist: nltk==3.9.1
Requires-Dist: ipython==8.28.0
Requires-Dist: snowflake-sqlalchemy==1.7.7
Requires-Dist: snowflake-connector-python==3.15.0
Requires-Dist: boto3==1.35.80
Requires-Dist: botocore==1.35.80
Requires-Dist: jmespath==1.0.1
Requires-Dist: s3transfer==0.10.0
Requires-Dist: moto==5.0.12
Requires-Dist: importlib-metadata==8.0.0
Requires-Dist: numpy==1.26.4
Dynamic: author
Dynamic: author-email
Dynamic: classifier
Dynamic: home-page
Dynamic: license
Dynamic: license-file
Dynamic: requires-dist
Dynamic: requires-python
Dynamic: summary
